mcd_stitcher/__init__.py
mcd_stitcher/mcd_convert.py
mcd_stitcher/mcd_stitch.py
mcd_stitcher/tiff_subset.py
mcd_stitcher-2.0.0.dist-info/licenses/LICENSE
mcd_stitcher-2.0.0.dist-info/METADATA
mcd_stitcher-2.0.0.dist-info/WHEEL
mcd_stitcher-2.0.0.dist-info/entry_points.txt
mcd_stitcher-2.0.0.dist-info/top_level.txt
mcd_stitcher-2.0.0.dist-info/RECORD
