Metadata-Version: 2.4
Name: mcd_stitcher
Version: 2.0.0
Summary: MCD to single tiffs, stitched tiff and tiff tools
Author-email: Pawan Chaurasia <pchaurasia98@gmail.com>
License: GPL-3.0
Project-URL: Homepage, https://github.com/PawanChaurasia/mcd_stitcher
Project-URL: Bug Tracker, https://github.com/PawanChaurasia/mcd_stitcher/issues
Project-URL: Repository, https://github.com/PawanChaurasia/mcd_stitcher
Keywords: imaging,masscytometry,StandardBio,SBT,IMC,stitching,conversion
Classifier: Programming Language :: Python :: 3
Classifier: License :: OSI Approved :: GNU General Public License v3 (GPLv3)
Classifier: Operating System :: OS Independent
Requires-Python: >=3.11
License-File: LICENSE
Requires-Dist: click
Requires-Dist: imagecodecs
Requires-Dist: numpy
Requires-Dist: pandas
Requires-Dist: readimc
Requires-Dist: scikit-image
Requires-Dist: tifffile
Dynamic: license-file
